plone.app.themingplugins-1.2-py3.12-nspkg.pth
plone/app/themingplugins/__init__.py
plone/app/themingplugins/configure.zcml
plone/app/themingplugins/testing.py
plone/app/themingplugins/browserlayer/__init__.py
plone/app/themingplugins/browserlayer/configure.zcml
plone/app/themingplugins/browserlayer/plugin.py
plone/app/themingplugins/browserlayer/schemata.py
plone/app/themingplugins/overrides/__init__.py
plone/app/themingplugins/overrides/configure.zcml
plone/app/themingplugins/overrides/plugin.py
plone/app/themingplugins/tests/__init__.py
plone/app/themingplugins/tests/configure.zcml
plone/app/themingplugins/tests/test_overrides.py
plone/app/themingplugins/tests/test_views.py
plone/app/themingplugins/tests/resources/css-js.xml
plone/app/themingplugins/tests/resources/manifest.cfg
plone/app/themingplugins/tests/resources/nonascii.html
plone/app/themingplugins/tests/resources/nonascii.xml
plone/app/themingplugins/tests/resources/othertheme.html
plone/app/themingplugins/tests/resources/overridesrules.xml
plone/app/themingplugins/tests/resources/overridestheme.html
plone/app/themingplugins/tests/resources/resource.css
plone/app/themingplugins/tests/resources/resource.js
plone/app/themingplugins/tests/resources/rules.xml
plone/app/themingplugins/tests/resources/theme.html
plone/app/themingplugins/tests/resources/overrides/plone.app.layout.viewlets.colophon.pt
plone/app/themingplugins/tests/resources/views/class-view.pt
plone/app/themingplugins/tests/resources/views/context-view.pt
plone/app/themingplugins/tests/resources/views/name-view.pt
plone/app/themingplugins/tests/resources/views/permission-view.pt
plone/app/themingplugins/tests/resources/views/test-view.pt
plone/app/themingplugins/tests/resources/views/views.cfg
plone/app/themingplugins/views/__init__.py
plone/app/themingplugins/views/configure.zcml
plone/app/themingplugins/views/plugin.py
plone.app.themingplugins-1.2.dist-info/METADATA
plone.app.themingplugins-1.2.dist-info/WHEEL
plone.app.themingplugins-1.2.dist-info/entry_points.txt
plone.app.themingplugins-1.2.dist-info/namespace_packages.txt
plone.app.themingplugins-1.2.dist-info/top_level.txt
plone.app.themingplugins-1.2.dist-info/RECORD
