Metadata-Version: 2.1
Name: plone.app.themingplugins
Version: 1.2
Summary: Plugins providing advanced plone.app.theming integration
Home-page: http://pypi.python.org/pypi/plone.app.theming.plugins
Author: Martin Aspeli
Author-email: optilude@gmail.com
License: GPL
Keywords: plone.app.theming diazo jbot views
Classifier: Framework :: Plone
Classifier: License :: OSI Approved :: GNU General Public License (GPL)
Classifier: Development Status :: 5 - Production/Stable
Classifier: Programming Language :: Python
Classifier: Programming Language :: Python :: 2
Classifier: Programming Language :: Python :: 2.7
Classifier: Programming Language :: Python :: 3
Classifier: Programming Language :: Python :: 3.7
Classifier: Programming Language :: Python :: 3.8
Classifier: Programming Language :: Python :: 3.9
Classifier: Programming Language :: Python :: 3.10
Classifier: Programming Language :: Python :: 3.11
Classifier: Programming Language :: Python :: 3.12
Requires-Python: >=2.7,!=3.0.*, !=3.1.*, !=3.2.*, !=3.3.*, !=3.4.*, !=3.5.*, !=3.6.*, <3.13
Requires-Dist: plone.app.theming
Requires-Dist: plone.resource
Requires-Dist: setuptools
Requires-Dist: six
Requires-Dist: z3c.jbot
Requires-Dist: zope.configuration
Requires-Dist: zope.dottedname
Requires-Dist: zope.interface
Provides-Extra: test
Requires-Dist: plone.app.testing ; extra == 'test'
